smashggAPI/__init__.py
smashggAPI/client.py
smashggAPI-0.0.2.dist-info/LICENSE
smashggAPI-0.0.2.dist-info/METADATA
smashggAPI-0.0.2.dist-info/WHEEL
smashggAPI-0.0.2.dist-info/top_level.txt
smashggAPI-0.0.2.dist-info/RECORD
