Metadata-Version: 2.1
Name: smashggAPI
Version: 0.0.2
Summary: A wrapper for smash.gg's GraphQL API
Home-page: https://github.com/keithrobichaud/smashgg-api-wrapper-python
Author: Keith Robichaud
Author-email: keith@smash.gg
License: UNKNOWN
Platform: UNKNOWN
Classifier: Programming Language :: Python :: 3
Classifier: License :: OSI Approved :: MIT License
Classifier: Operating System :: OS Independent
